llm_context_builder/__init__.py
llm_context_builder/main.py
llm_context_builder/project_detector.py
llm_context_builder/exporters/__init__.py
llm_context_builder/exporters/base_exporter.py
llm_context_builder-1.0.0.dist-info/METADATA
llm_context_builder-1.0.0.dist-info/WHEEL
llm_context_builder-1.0.0.dist-info/entry_points.txt
llm_context_builder-1.0.0.dist-info/top_level.txt
llm_context_builder-1.0.0.dist-info/RECORD
