Metadata-Version: 2.4
Name: llm-context-builder
Version: 1.0.0
Summary: Export any project to a single text file optimized for LLM context
Home-page: https://github.com/yourusername/llm-context-builder
Author: Your Name
Author-email: Your Name <your.email@example.com>
License: MIT
Project-URL: Homepage, https://github.com/yourusername/llm-context-builder
Project-URL: Bug Reports, https://github.com/yourusername/llm-context-builder/issues
Project-URL: Source, https://github.com/yourusername/llm-context-builder
Keywords: llm,context,export,project,documentation,ai
Classifier: Development Status :: 4 - Beta
Classifier: Intended Audience :: Developers
Classifier: Topic :: Software Development :: Documentation
Classifier: Topic :: Software Development :: Build Tools
Classifier: License :: OSI Approved :: MIT License
Classifier: Programming Language :: Python :: 3
Classifier: Programming Language :: Python :: 3.8
Classifier: Programming Language :: Python :: 3.9
Classifier: Programming Language :: Python :: 3.10
Classifier: Programming Language :: Python :: 3.11
Classifier: Programming Language :: Python :: 3.12
Requires-Python: >=3.8
Requires-Dist: click>=8.0.0
Requires-Dist: colorama>=0.4.0
Requires-Dist: pathspec>=0.10.0
Provides-Extra: tokens
Requires-Dist: tiktoken>=0.4.0; extra == "tokens"
Provides-Extra: dev
Requires-Dist: pytest>=7.0.0; extra == "dev"
Requires-Dist: black>=22.0.0; extra == "dev"
Requires-Dist: flake8>=4.0.0; extra == "dev"
Requires-Dist: mypy>=1.0.0; extra == "dev"
Dynamic: author
Dynamic: home-page
Dynamic: requires-python
